avilla/onebot/__init__.py
avilla/onebot/ability.py
avilla/onebot/config.py
avilla/onebot/element_tree.py
avilla/onebot/elements.py
avilla/onebot/event.py
avilla/onebot/event_tree.py
avilla/onebot/execution_ensure.py
avilla/onebot/message_serializer.py
avilla/onebot/profile.py
avilla/onebot/protocol.py
avilla/onebot/resp.py
avilla_onebot-0.0.7.dist-info/LICENSE
avilla_onebot-0.0.7.dist-info/WHEEL
avilla_onebot-0.0.7.dist-info/METADATA
avilla_onebot-0.0.7.dist-info/RECORD
